btdht/__init__.py
btdht/dht.c
btdht/dht.cp36-win_amd64.pyd
btdht/dht.pyx
btdht/exceptions.py
btdht/krcp.c
btdht/krcp.cp36-win_amd64.pyd
btdht/krcp.pxd
btdht/krcp.pyx
btdht/utils.c
btdht/utils.cp36-win_amd64.pyd
btdht/utils.pyx
btdht-0.3.3.dist-info/LICENSE
btdht-0.3.3.dist-info/METADATA
btdht-0.3.3.dist-info/WHEEL
btdht-0.3.3.dist-info/top_level.txt
btdht-0.3.3.dist-info/RECORD
